labtasker_plugin_task_recency/__init__.py
labtasker_plugin_task_recency/impl.py
labtasker_plugin_task_recency/main.py
labtasker_plugin_task_recency-0.1.1.dist-info/METADATA
labtasker_plugin_task_recency-0.1.1.dist-info/WHEEL
labtasker_plugin_task_recency-0.1.1.dist-info/entry_points.txt
labtasker_plugin_task_recency-0.1.1.dist-info/top_level.txt
labtasker_plugin_task_recency-0.1.1.dist-info/RECORD
